freesurfer_stats/__init__.py
freesurfer_stats/version.py
freesurfer_stats-1.2.1.dist-info/COPYING
freesurfer_stats-1.2.1.dist-info/METADATA
freesurfer_stats-1.2.1.dist-info/WHEEL
freesurfer_stats-1.2.1.dist-info/top_level.txt
freesurfer_stats-1.2.1.dist-info/RECORD
