Metadata-Version: 2.1
Name: freesurfer-stats
Version: 1.2.1
Summary: Python Library to Read FreeSurfer's cortical parcellation anatomical statistics
Home-page: https://github.com/fphammerle/freesurfer-stats
Author: Fabian Peter Hammerle
Author-email: fabian@hammerle.me
License: GPLv3+
Keywords: anatomy,aparc,area,brain,cortex,dataframe,freesurfer,mris_anatomical_stats,neuroimaging,pandas,parcellation,reader,statistics,surface,volume
Platform: UNKNOWN
Classifier: Development Status :: 4 - Beta
Classifier: Intended Audience :: Healthcare Industry
Classifier: Intended Audience :: Science/Research
Classifier: License :: OSI Approved :: GNU General Public License v3 or later (GPLv3+)
Classifier: Programming Language :: Python :: 3.5
Classifier: Programming Language :: Python :: 3.6
Classifier: Programming Language :: Python :: 3.7
Classifier: Programming Language :: Python :: 3.8
Classifier: Topic :: Scientific/Engineering :: Information Analysis
Classifier: Topic :: Scientific/Engineering :: Medical Science Apps.
Classifier: Topic :: Utilities
Requires-Dist: numpy (<2)
Requires-Dist: pandas (<2,>=0.21)
